seqgra/__init__.py
seqgra/constants.py
seqgra/data-config.xsd
seqgra/idresolver.py
seqgra/misc.py
seqgra/model-config.xsd
seqgra/schema.py
seqgra/seqgra.py
seqgra/seqgraa.py
seqgra/seqgrae.py
seqgra/seqgras.py
seqgra/comparator/__init__.py
seqgra/comparator/comparator.py
seqgra/comparator/curvetablecomparator.py
seqgra/comparator/fietablecomparator.py
seqgra/comparator/prcomparator.py
seqgra/comparator/roccomparator.py
seqgra/comparator/tablecomparator.py
seqgra/evaluator/__init__.py
seqgra/evaluator/evaluator.py
seqgra/evaluator/gradientbased.py
seqgra/evaluator/metricsevaluator.py
seqgra/evaluator/plotagreement.R
seqgra/evaluator/predictevaluator.py
seqgra/evaluator/prevaluator.py
seqgra/evaluator/rocevaluator.py
seqgra/evaluator/saliencyevaluator.py
seqgra/evaluator/sisevaluator.py
seqgra/evaluator/explainer/__init__.py
seqgra/evaluator/explainer/backprop.py
seqgra/evaluator/explainer/deeplift.py
seqgra/evaluator/explainer/feedback.py
seqgra/evaluator/explainer/gradcam.py
seqgra/evaluator/explainer/occlusion.py
seqgra/evaluator/explainer/path.py
seqgra/evaluator/explainer/patterns.py
seqgra/evaluator/explainer/perturbation.py
seqgra/evaluator/explainer/ebp/__init__.py
seqgra/evaluator/explainer/ebp/ebp.py
seqgra/evaluator/explainer/ebp/functions.py
seqgra/evaluator/explainer/real_time/__init__.py
seqgra/evaluator/explainer/real_time/pytorch_fixes.py
seqgra/evaluator/explainer/real_time/resnet_encoder.py
seqgra/evaluator/explainer/real_time/saliency_eval.py
seqgra/evaluator/gradientbased/__init__.py
seqgra/evaluator/gradientbased/abstractdifferencegradientevaluator.py
seqgra/evaluator/gradientbased/abstractgradientevaluator.py
seqgra/evaluator/gradientbased/contrastiveexcitationbackpropevaluator.py
seqgra/evaluator/gradientbased/deconvevaluator.py
seqgra/evaluator/gradientbased/deepliftevaluator.py
seqgra/evaluator/gradientbased/differencegradientevaluator.py
seqgra/evaluator/gradientbased/ebphelper.py
seqgra/evaluator/gradientbased/excitationbackpropevaluator.py
seqgra-0.0.4.dist-info/LICENSE
seqgra-0.0.4.dist-info/METADATA
seqgra-0.0.4.dist-info/WHEEL
seqgra-0.0.4.dist-info/entry_points.txt
seqgra-0.0.4.dist-info/top_level.txt
seqgra-0.0.4.dist-info/RECORD
