Metadata-Version: 2.1
Name: seqgra
Version: 0.0.4
Summary: Synthetic rule-based biological sequence data generation for architecture evaluation and search
Home-page: https://kkrismer.github.io/seqgra/
Author: Konstantin Krismer
Author-email: krismer@mit.edu
License: MIT License
Platform: UNKNOWN
Classifier: Development Status :: 4 - Beta
Classifier: Environment :: Console
Classifier: Intended Audience :: Science/Research
Classifier: License :: OSI Approved :: MIT License
Classifier: Operating System :: OS Independent
Classifier: Programming Language :: Python :: 3
Requires-Python: >=3
License-File: LICENSE
Requires-Dist: Cython (>=0.29)
Requires-Dist: lxml (>=4.4.1)
Requires-Dist: matplotlib (>=3.1)
Requires-Dist: numpy (>=1.14)
Requires-Dist: pandas (>=0.25)
Requires-Dist: PyYAML (>=5.3)
Requires-Dist: scikit-image (>=0.16)
Requires-Dist: scikit-learn (>=0.21)
Requires-Dist: scipy (>=1.3)
Requires-Dist: setuptools (>=42)
Requires-Dist: ushuffle (>=1.1.2)
